pyhotty/__init__.py
pyhotty/__main__.py
pyhotty/py.typed
pyhotty/pyhotty.py
pyhotty-0.0.7.dist-info/LICENSE
pyhotty-0.0.7.dist-info/METADATA
pyhotty-0.0.7.dist-info/WHEEL
pyhotty-0.0.7.dist-info/entry_points.txt
pyhotty-0.0.7.dist-info/RECORD
