Metadata-Version: 2.1
Name: pyhotty
Version: 0.0.7
Summary: Pyhotty
Home-page: https://github.com/nanosystemslab/pyhotty
License: GPL-3.0
Author: Nanosystems Lab
Author-email: fnslab@hawaii.edu
Requires-Python: >=3.9,<4.0
Classifier: Development Status :: 5 - Production/Stable
Classifier: License :: OSI Approved :: GNU General Public License v3 (GPLv3)
Classifier: Programming Language :: Python :: 3
Classifier: Programming Language :: Python :: 3.9
Classifier: Programming Language :: Python :: 3.10
Classifier: Programming Language :: Python :: 3.11
Classifier: Programming Language :: Python :: 3.12
Requires-Dist: argparse (>=1.4.0)
Requires-Dist: minimalmodbus (>=2.1.1)
Project-URL: Changelog, https://github.com/nanosystemslab/pyhotty/releases
Project-URL: Documentation, https://pyhotty.readthedocs.io
Project-URL: Repository, https://github.com/nanosystemslab/pyhotty
